scribd_dl/__init__.py
scribd_dl/scribd_dl.py
scribd_dl/utils.py
scribd_dl/version.py
scribd_dl/assets/README.txt
scribd_dl-0.4.5.dist-info/DESCRIPTION.rst
scribd_dl-0.4.5.dist-info/METADATA
scribd_dl-0.4.5.dist-info/RECORD
scribd_dl-0.4.5.dist-info/WHEEL
scribd_dl-0.4.5.dist-info/entry_points.txt
scribd_dl-0.4.5.dist-info/metadata.json
scribd_dl-0.4.5.dist-info/top_level.txt
