Metadata-Version: 2.0
Name: scribd-dl
Version: 0.4.5
Summary: Command-line program to download Scribd documents in pdf format
Home-page: https://github.com/giannisterzopoulos/scribd-dl
Author: Giannis Terzopoulos
Author-email: terzo.giannis@gmail.com
License: MIT license
Keywords: scribd_dl
Platform: UNKNOWN
Classifier: Development Status :: 4 - Beta
Classifier: Intended Audience :: Developers
Classifier: License :: OSI Approved :: MIT License
Classifier: Natural Language :: English
Classifier: Programming Language :: Python :: 3
Classifier: Programming Language :: Python :: 3.4
Classifier: Programming Language :: Python :: 3.5
Classifier: Programming Language :: Python :: 3.6
Requires-Dist: selenium (>=3.8.0)
Requires-Dist: Pillow (>=4.0.0)
Requires-Dist: img2pdf (>=0.2.3)
Requires-Dist: requests (>=2.10.0)
